README.md
setup.py
wavcat/__init__.py
wavcat.egg-info/PKG-INFO
wavcat.egg-info/SOURCES.txt
wavcat.egg-info/dependency_links.txt
wavcat.egg-info/top_level.txt