Metadata-Version: 2.1
Name: wavcat
Version: 0.0.1
Summary: An easy-to-use library for WaveCat
Home-page: https://wav.cat
Author: VMOON
Author-email: hi@vmoon.org
License: UNKNOWN
Platform: UNKNOWN
